.gitignore
035365c5d53e19820b62__mypyc.cpython-312-x86_64-linux-gnu.so
asgi_context/headers_extrator.py
asgi_context/context.py
asgi_context/protocol.cpython-312-x86_64-linux-gnu.so
asgi_context/__init__.cpython-312-x86_64-linux-gnu.so
asgi_context/headers_extrator.cpython-312-x86_64-linux-gnu.so
asgi_context/__init__.py
asgi_context/context.cpython-312-x86_64-linux-gnu.so
asgi_context/protocol.py
asgi_context-0.2.1.dist-info/WHEEL
asgi_context-0.2.1.dist-info/RECORD
asgi_context-0.2.1.dist-info/METADATA
asgi_context-0.2.1.dist-info/licenses/LICENSE
