Metadata-Version: 2.1
Name: asgi_context
Version: 0.2.1
Summary: Simple request context for ASGI compatible applications
Author-Email: Marcin Paliwoda <boringstuffinc@gmail.com>
License: MIT
Requires-Python: >=3.10
Requires-Dist: mypy-extensions>=1.0.0
